aliyunsdkonsmqtt/__init__.py
aliyunsdkonsmqtt/endpoint.py
aliyunsdkonsmqtt/request/__init__.py
aliyunsdkonsmqtt/request/v20200420/ApplyTokenRequest.py
aliyunsdkonsmqtt/request/v20200420/BatchQuerySessionByClientIdsRequest.py
aliyunsdkonsmqtt/request/v20200420/CreateGroupIdRequest.py
aliyunsdkonsmqtt/request/v20200420/DeleteGroupIdRequest.py
aliyunsdkonsmqtt/request/v20200420/GetDeviceCredentialRequest.py
aliyunsdkonsmqtt/request/v20200420/ListGroupIdRequest.py
aliyunsdkonsmqtt/request/v20200420/QuerySessionByClientIdRequest.py
aliyunsdkonsmqtt/request/v20200420/QueryTokenRequest.py
aliyunsdkonsmqtt/request/v20200420/RefreshDeviceCredentialRequest.py
aliyunsdkonsmqtt/request/v20200420/RegisterDeviceCredentialRequest.py
aliyunsdkonsmqtt/request/v20200420/RevokeTokenRequest.py
aliyunsdkonsmqtt/request/v20200420/SendMessageRequest.py
aliyunsdkonsmqtt/request/v20200420/UnRegisterDeviceCredentialRequest.py
aliyunsdkonsmqtt/request/v20200420/__init__.py
aliyun_python_sdk_onsmqtt-1.0.5.dist-info/LICENSE
aliyun_python_sdk_onsmqtt-1.0.5.dist-info/METADATA
aliyun_python_sdk_onsmqtt-1.0.5.dist-info/WHEEL
aliyun_python_sdk_onsmqtt-1.0.5.dist-info/top_level.txt
aliyun_python_sdk_onsmqtt-1.0.5.dist-info/RECORD
